setup.py
WorkFlowUtilsHS.egg-info/PKG-INFO
WorkFlowUtilsHS.egg-info/SOURCES.txt
WorkFlowUtilsHS.egg-info/dependency_links.txt
WorkFlowUtilsHS.egg-info/requires.txt
WorkFlowUtilsHS.egg-info/top_level.txt
Workflow_HS/__init__.py
Workflow_HS/Edge/BaseEdge.py
Workflow_HS/Edge/NormalEdge.py
Workflow_HS/Edge/__init__.py
Workflow_HS/Factory/Executor.py
Workflow_HS/Factory/GraphTool.py
Workflow_HS/Factory/Tools.py
Workflow_HS/Factory/__init__.py
Workflow_HS/Transfor/GraphNode.py
Workflow_HS/Transfor/NodeTrans.py
Workflow_HS/Transfor/__init__.py
Workflow_HS/Victor/BaseVictor.py
Workflow_HS/Victor/BranchVictor.py
Workflow_HS/Victor/ContainerVictor.py
Workflow_HS/Victor/EndVictor.py
Workflow_HS/Victor/StartVictor.py
Workflow_HS/Victor/WorkflowVictor.py
Workflow_HS/Victor/__init__.py