Metadata-Version: 2.1
Name: WorkFlowUtilsHS
Version: 0.2.0
Summary: Allen.huang's private utils
Home-page: https://hs-personproject.coding.net/p/ttt/d/workflow/git
Author: Allen.huang
Author-email: fengyeyoni@163.com
License: MIT Licence
Keywords: pip,WorkFlowUtilsHS
Platform: any
